sslmanage/__init__.py
sslmanage/base.py
sslmanage/qiniu_ssl.py
sslmanage/test.py
sslmanage/upyun_ssl.py
sslmanage-1.0.4.dist-info/METADATA
sslmanage-1.0.4.dist-info/WHEEL
sslmanage-1.0.4.dist-info/top_level.txt
sslmanage-1.0.4.dist-info/RECORD
