Metadata-Version: 2.1
Name: sslmanage
Version: 1.0.4
Summary: 七牛，又拍云证书更新
Home-page: https://github.com/Angel-fund/sslmanage
Author: osmen
Author-email: lijiguan1@gmail.com
License: BSD License
Keywords: 七牛，又拍云证书更新
Platform: UNKNOWN
Classifier: Programming Language :: Python :: 3.6
Requires-Dist: requests (==2.20.1)
Requires-Dist: qiniu (==7.1.4)
